{
  "UserEvents": {
    "jusjohns": [
      {
        "NewName": "ConnectToServerGum.TextBoxInstance",
        "OldName": null,
        "ElementType": "Screens",
        "EventType": 5,
        "TimestampUtc": "2023-09-21T17:57:02.894424Z"
      },
      {
        "NewName": "ConnectToServerGum.LabelInstance",
        "OldName": null,
        "ElementType": "Screens",
        "EventType": 5,
        "TimestampUtc": "2023-09-21T17:58:05.8349634Z"
      },
      {
        "NewName": "ConnectToServerGum.IpTextbox",
        "OldName": "ConnectToServerGum.TextBoxInstance",
        "ElementType": "Screens",
        "EventType": 7,
        "TimestampUtc": "2023-09-21T17:58:16.0570844Z"
      },
      {
        "NewName": "ConnectToServerGum.NineSliceInstance",
        "OldName": null,
        "ElementType": "Screens",
        "EventType": 5,
        "TimestampUtc": "2023-09-21T17:58:43.1857714Z"
      },
      {
        "NewName": "ConnectToServerGum.ServerJoinPanel",
        "OldName": "ConnectToServerGum.NineSliceInstance",
        "ElementType": "Screens",
        "EventType": 7,
        "TimestampUtc": "2023-09-21T17:58:48.0198304Z"
      },
      {
        "NewName": "ConnectToServerGum.ContainerInstance",
        "OldName": null,
        "ElementType": "Screens",
        "EventType": 5,
        "TimestampUtc": "2023-09-21T17:59:19.7312875Z"
      },
      {
        "NewName": "ConnectToServerGum.MarginContainer",
        "OldName": "ConnectToServerGum.ContainerInstance",
        "ElementType": "Screens",
        "EventType": 7,
        "TimestampUtc": "2023-09-21T17:59:24.907949Z"
      },
      {
        "NewName": null,
        "OldName": "ConnectToServerGum.Elements/Label LabelInstance in ConnectToServerGum",
        "ElementType": "Screens",
        "EventType": 6,
        "TimestampUtc": "2023-09-21T18:01:08.6101918Z"
      },
      {
        "NewName": "ConnectToServerGum.TextInstance",
        "OldName": null,
        "ElementType": "Screens",
        "EventType": 5,
        "TimestampUtc": "2023-09-21T18:01:11.2487851Z"
      },
      {
        "NewName": "ConnectToServerGum.ButtonConfirmInstance",
        "OldName": null,
        "ElementType": "Screens",
        "EventType": 5,
        "TimestampUtc": "2023-09-21T18:02:31.0292989Z"
      },
      {
        "NewName": "ConnectToServerGum.JoinButton",
        "OldName": "ConnectToServerGum.ButtonConfirmInstance",
        "ElementType": "Screens",
        "EventType": 7,
        "TimestampUtc": "2023-09-21T18:04:21.9500884Z"
      },
      {
        "NewName": "ConnectToServerGum.Title",
        "OldName": "ConnectToServerGum.TextInstance",
        "ElementType": "Screens",
        "EventType": 7,
        "TimestampUtc": "2023-09-21T18:04:26.460093Z"
      },
      {
        "NewName": "ConnectToServerGum.ButtonDenyInstance",
        "OldName": null,
        "ElementType": "Screens",
        "EventType": 5,
        "TimestampUtc": "2023-09-21T18:04:42.0682254Z"
      },
      {
        "NewName": "ConnectToServerGum.ContainerInstance",
        "OldName": null,
        "ElementType": "Screens",
        "EventType": 5,
        "TimestampUtc": "2023-09-21T18:04:52.5558428Z"
      },
      {
        "NewName": "ConnectToServerGum.ButtonRow",
        "OldName": "ConnectToServerGum.ContainerInstance",
        "ElementType": "Screens",
        "EventType": 7,
        "TimestampUtc": "2023-09-21T18:04:55.6678838Z"
      },
      {
        "NewName": "ConnectToServerGum.CancelButton",
        "OldName": "ConnectToServerGum.ButtonDenyInstance",
        "ElementType": "Screens",
        "EventType": 7,
        "TimestampUtc": "2023-09-21T18:05:03.1322029Z"
      },
      {
        "NewName": "ConnectToServerGum.IpTextbox1",
        "OldName": null,
        "ElementType": "Screens",
        "EventType": 5,
        "TimestampUtc": "2023-09-21T18:19:12.3784624Z"
      },
      {
        "NewName": "ConnectToServerGum.UsernameTextbox",
        "OldName": "ConnectToServerGum.IpTextbox1",
        "ElementType": "Screens",
        "EventType": 7,
        "TimestampUtc": "2023-09-21T18:19:39.9731761Z"
      },
      {
        "NewName": "ConnectToServerGum.Title1",
        "OldName": null,
        "ElementType": "Screens",
        "EventType": 5,
        "TimestampUtc": "2023-09-21T18:19:55.7431536Z"
      },
      {
        "NewName": "ConnectToServerGum.UsernameLabel",
        "OldName": "ConnectToServerGum.Title1",
        "ElementType": "Screens",
        "EventType": 7,
        "TimestampUtc": "2023-09-21T18:20:03.5487488Z"
      },
      {
        "NewName": "ConnectToServerGum.AddressLabel",
        "OldName": "ConnectToServerGum.Title",
        "ElementType": "Screens",
        "EventType": 7,
        "TimestampUtc": "2023-09-21T18:20:10.2291847Z"
      },
      {
        "NewName": "ServerLobbyGum.NineSliceInstance",
        "OldName": null,
        "ElementType": "Screens",
        "EventType": 5,
        "TimestampUtc": "2023-09-21T18:36:07.4935905Z"
      },
      {
        "NewName": "ServerLobbyGum.UsersPanel",
        "OldName": "ServerLobbyGum.NineSliceInstance",
        "ElementType": "Screens",
        "EventType": 7,
        "TimestampUtc": "2023-09-21T18:36:15.013698Z"
      },
      {
        "NewName": "ServerLobbyGum.ContainerInstance",
        "OldName": null,
        "ElementType": "Screens",
        "EventType": 5,
        "TimestampUtc": "2023-09-21T18:36:30.4108446Z"
      },
      {
        "NewName": "ServerLobbyGum.MarginContainer",
        "OldName": "ServerLobbyGum.ContainerInstance",
        "ElementType": "Screens",
        "EventType": 7,
        "TimestampUtc": "2023-09-21T18:36:34.2696355Z"
      },
      {
        "NewName": null,
        "OldName": "ServerLobbyGum.NineSlice UsersPanel in ServerLobbyGum",
        "ElementType": "Screens",
        "EventType": 6,
        "TimestampUtc": "2023-09-21T18:36:41.1529623Z"
      },
      {
        "NewName": null,
        "OldName": "ServerLobbyGum.Container MarginContainer in ServerLobbyGum",
        "ElementType": "Screens",
        "EventType": 6,
        "TimestampUtc": "2023-09-21T18:36:42.9845663Z"
      },
      {
        "NewName": "Menus/ServerLobby",
        "OldName": null,
        "ElementType": "Components",
        "EventType": 0,
        "TimestampUtc": "2023-09-21T18:40:21.8673854Z"
      },
      {
        "NewName": "Menus/ServerLobby (Container).NineSliceInstance",
        "OldName": null,
        "ElementType": "Components",
        "EventType": 5,
        "TimestampUtc": "2023-09-21T18:40:44.2916341Z"
      },
      {
        "NewName": "Menus/ServerLobby (Container).LobbyMembersPanel",
        "OldName": "Menus/ServerLobby (Container).NineSliceInstance",
        "ElementType": "Components",
        "EventType": 7,
        "TimestampUtc": "2023-09-21T18:40:55.4225909Z"
      },
      {
        "NewName": "Menus/ServerLobby (Container).NineSliceInstance",
        "OldName": null,
        "ElementType": "Components",
        "EventType": 5,
        "TimestampUtc": "2023-09-21T18:47:48.1550121Z"
      },
      {
        "NewName": "Menus/ServerLobby (Container).ChatPanel",
        "OldName": "Menus/ServerLobby (Container).NineSliceInstance",
        "ElementType": "Components",
        "EventType": 7,
        "TimestampUtc": "2023-09-21T18:47:57.0065586Z"
      },
      {
        "NewName": "Menus/ServerLobby (Container).ListBoxInstance",
        "OldName": null,
        "ElementType": "Components",
        "EventType": 5,
        "TimestampUtc": "2023-09-21T18:49:12.274808Z"
      },
      {
        "NewName": "Menus/ServerLobby (Container).TextBoxInstance",
        "OldName": null,
        "ElementType": "Components",
        "EventType": 5,
        "TimestampUtc": "2023-09-21T18:49:41.3715173Z"
      },
      {
        "NewName": "Menus/ServerLobby (Container).ChatEntryBox",
        "OldName": "Menus/ServerLobby (Container).TextBoxInstance",
        "ElementType": "Components",
        "EventType": 7,
        "TimestampUtc": "2023-09-21T18:49:46.1189428Z"
      },
      {
        "NewName": "Menus/ServerLobby (Container).ListBoxInstance1",
        "OldName": null,
        "ElementType": "Components",
        "EventType": 5,
        "TimestampUtc": "2023-09-21T18:51:48.4507287Z"
      },
      {
        "NewName": "Menus/ServerLobby (Container).PlayersList",
        "OldName": "Menus/ServerLobby (Container).ListBoxInstance1",
        "ElementType": "Components",
        "EventType": 7,
        "TimestampUtc": "2023-09-21T18:52:15.3396387Z"
      },
      {
        "NewName": "Menus/ServerLobby (Container).ChatsList",
        "OldName": "Menus/ServerLobby (Container).ListBoxInstance",
        "ElementType": "Components",
        "EventType": 7,
        "TimestampUtc": "2023-09-21T18:52:20.4205036Z"
      },
      {
        "NewName": "Menus/ServerLobby (Container).ContainerInstance",
        "OldName": null,
        "ElementType": "Components",
        "EventType": 5,
        "TimestampUtc": "2023-09-21T18:52:35.3558575Z"
      },
      {
        "NewName": "Menus/ServerLobby (Container).ChatInputContainer",
        "OldName": "Menus/ServerLobby (Container).ContainerInstance",
        "ElementType": "Components",
        "EventType": 7,
        "TimestampUtc": "2023-09-21T18:52:47.0066863Z"
      },
      {
        "NewName": "Menus/ServerLobby (Container).ButtonConfirmInstance",
        "OldName": null,
        "ElementType": "Components",
        "EventType": 5,
        "TimestampUtc": "2023-09-21T18:53:22.6648458Z"
      },
      {
        "NewName": "Menus/ServerLobby (Container).SendChatButton",
        "OldName": "Menus/ServerLobby (Container).ButtonConfirmInstance",
        "ElementType": "Components",
        "EventType": 7,
        "TimestampUtc": "2023-09-21T18:53:30.3905533Z"
      },
      {
        "NewName": "Menus/ServerLobby (Container).ChatEntryTextBox",
        "OldName": "Menus/ServerLobby (Container).ChatEntryBox",
        "ElementType": "Components",
        "EventType": 7,
        "TimestampUtc": "2023-09-21T19:02:56.1439682Z"
      },
      {
        "NewName": "ServerLobbyGum.ServerLobbyInstance",
        "OldName": null,
        "ElementType": "Screens",
        "EventType": 5,
        "TimestampUtc": "2023-09-21T19:07:43.2128847Z"
      },
      {
        "NewName": "ServerLobbyGum.ServerLobbyMenu",
        "OldName": "ServerLobbyGum.ServerLobbyInstance",
        "ElementType": "Screens",
        "EventType": 7,
        "TimestampUtc": "2023-09-21T19:07:48.7910742Z"
      },
      {
        "NewName": "Menus/ServerLobby (Container).ButtonConfirmInstance",
        "OldName": null,
        "ElementType": "Components",
        "EventType": 5,
        "TimestampUtc": "2023-09-21T20:08:48.2077072Z"
      },
      {
        "NewName": "Menus/ServerLobby (Container).ReadyButton",
        "OldName": "Menus/ServerLobby (Container).ButtonConfirmInstance",
        "ElementType": "Components",
        "EventType": 7,
        "TimestampUtc": "2023-09-21T20:08:55.4003442Z"
      },
      {
        "NewName": "Controls/ListBoxItemPlayer",
        "OldName": null,
        "ElementType": "Components",
        "EventType": 0,
        "TimestampUtc": "2023-09-21T20:10:32.3206678Z"
      },
      {
        "NewName": "Controls/ListBoxItemPlayer (Container).IconInstance",
        "OldName": null,
        "ElementType": "Components",
        "EventType": 5,
        "TimestampUtc": "2023-09-21T20:10:50.175344Z"
      },
      {
        "NewName": "Controls/ListBoxItemPlayer (Container).ReadyIcon",
        "OldName": "Controls/ListBoxItemPlayer (Container).IconInstance",
        "ElementType": "Components",
        "EventType": 7,
        "TimestampUtc": "2023-09-21T20:14:51.6436802Z"
      },
      {
        "NewName": "Controls/ListBoxItemPlayer (Container).ReadyIcon",
        "OldName": "Controls/ListBoxItemPlayer (Container).IconInstance",
        "ElementType": "Components",
        "EventType": 7,
        "TimestampUtc": "2023-09-21T20:14:51.6446801Z"
      },
      {
        "NewName": "Controls/ListBoxItemPlayer (Container).ReadyIcon",
        "OldName": "Controls/ListBoxItemPlayer (Container).IconInstance",
        "ElementType": "Components",
        "EventType": 7,
        "TimestampUtc": "2023-09-21T20:14:51.6506817Z"
      },
      {
        "NewName": "Controls/ListBoxItemPlayer (Container).ReadyIcon",
        "OldName": "Controls/ListBoxItemPlayer (Container).IconInstance",
        "ElementType": "Components",
        "EventType": 7,
        "TimestampUtc": "2023-09-21T20:14:51.664686Z"
      },
      {
        "NewName": "Controls/ListBoxItemPlayer (Container).ReadyIcon",
        "OldName": "Controls/ListBoxItemPlayer (Container).IconInstance",
        "ElementType": "Components",
        "EventType": 7,
        "TimestampUtc": "2023-09-21T20:14:51.6656861Z"
      },
      {
        "NewName": "Controls/ListBoxItemPlayer (Container).ReadyIcon1",
        "OldName": null,
        "ElementType": "Components",
        "EventType": 5,
        "TimestampUtc": "2023-09-21T20:14:54.1401604Z"
      },
      {
        "NewName": "Controls/ListBoxItemPlayer (Container).NetworkIcon",
        "OldName": "Controls/ListBoxItemPlayer (Container).ReadyIcon1",
        "ElementType": "Components",
        "EventType": 7,
        "TimestampUtc": "2023-09-21T20:14:57.9716219Z"
      },
      {
        "NewName": "Controls/ListBoxItemPlayer (Container).NetworkIcon",
        "OldName": "Controls/ListBoxItemPlayer (Container).ReadyIcon1",
        "ElementType": "Components",
        "EventType": 7,
        "TimestampUtc": "2023-09-21T20:14:57.9726245Z"
      },
      {
        "NewName": "Controls/ListBoxItemPlayer (Container).NetworkIcon",
        "OldName": "Controls/ListBoxItemPlayer (Container).ReadyIcon1",
        "ElementType": "Components",
        "EventType": 7,
        "TimestampUtc": "2023-09-21T20:14:57.9796261Z"
      },
      {
        "NewName": "Controls/ListBoxItemPlayer (Container).NetworkIcon",
        "OldName": "Controls/ListBoxItemPlayer (Container).ReadyIcon1",
        "ElementType": "Components",
        "EventType": 7,
        "TimestampUtc": "2023-09-21T20:14:57.9866276Z"
      },
      {
        "NewName": "Controls/ListBoxItemPlayer (Container).NetworkIcon",
        "OldName": "Controls/ListBoxItemPlayer (Container).ReadyIcon1",
        "ElementType": "Components",
        "EventType": 7,
        "TimestampUtc": "2023-09-21T20:14:57.9916285Z"
      }
    ]
  }
}